freqtrade_bots_storage/__init__.py
freqtrade_bots_storage/models/__init__.py
freqtrade_bots_storage/models/bot_state.py
freqtrade_bots_storage/protocol/__init__.py
freqtrade_bots_storage/protocol/protocol.py
freqtrade_bots_storage/storages/__init__.py
freqtrade_bots_storage/storages/file_storage/__init__.py
freqtrade_bots_storage/storages/file_storage/file_tradig_bots_storage.py
freqtrade_bots_storage-0.0.31.dist-info/licenses/LICENSE
freqtrade_bots_storage-0.0.31.dist-info/METADATA
freqtrade_bots_storage-0.0.31.dist-info/WHEEL
freqtrade_bots_storage-0.0.31.dist-info/top_level.txt
freqtrade_bots_storage-0.0.31.dist-info/RECORD
