Metadata-Version: 2.4
Name: freqtrade-bots-storage
Version: 0.0.31
Summary: A persistent storage for freqtrade bots
Requires-Python: >=3.12
License-File: LICENSE
Requires-Dist: uuid-utils>=0.10.0
Dynamic: license-file
